cyyjson.cpython-38-darwin.so
yyjson-3.0.1.dist-info/RECORD
yyjson-3.0.1.dist-info/LICENSE
yyjson-3.0.1.dist-info/WHEEL
yyjson-3.0.1.dist-info/top_level.txt
yyjson-3.0.1.dist-info/METADATA
yyjson/__init__.pyi
yyjson/__init__.py
