Metadata-Version: 2.1
Name: yyjson
Version: 3.0.1
Summary: yyjson bindings for python
Home-page: https://github.com/TkTech/py_yyjson
Author: Tyler Kennedy
Author-email: tk@tkte.ch
Keywords: json,yyjson
Classifier: Programming Language :: Python :: 3
Classifier: License :: OSI Approved :: MIT License
Classifier: Operating System :: OS Independent
Classifier: Development Status :: 3 - Alpha
Classifier: Intended Audience :: Developers
Requires-Python: >=3.8
License-File: LICENSE
Provides-Extra: release
Requires-Dist: sphinx ; extra == 'release'
Requires-Dist: sphinx-copybutton ; extra == 'release'
Requires-Dist: ghp-import ; extra == 'release'
Requires-Dist: bumpversion ; extra == 'release'
Requires-Dist: black ; extra == 'release'
Requires-Dist: furo ; extra == 'release'
Provides-Extra: test
Requires-Dist: pytest ; extra == 'test'
